keyloggerthread/__init__.py
keyloggerthread/main.py
keylogger_thread-0.1.dist-info/METADATA
keylogger_thread-0.1.dist-info/WHEEL
keylogger_thread-0.1.dist-info/top_level.txt
keylogger_thread-0.1.dist-info/RECORD
