Metadata-Version: 2.1
Name: keylogger-thread
Version: 0.1
Summary: A Python package for easily logging keys.
